{
    "filename":"DS5",
    "file_description":"",
    "linezone":{
        "start": [634,400],
        "end":[635,400]
    },
    "lanes": {
        "n1_start": [426,400],
        "n1_end":[477,400],
        "n2_start":[477,400],
        "n2_end":[531,400],
        "n3_start":[531,400],
        "n3_end":[587,400],

        "s1_start": [688,400],
        "s1_end":[748,400],
        "s2_start":[748,400],
        "s2_end":[806,400],
        "s3_start":[806,400],
        "s3_end":[867,400]
    },
    "vehicle_counts":{
        "total":248,
        "total_n":121,
        "total_s":127,
        "total_light":233,
        "total_heavy":14,
        "total_bus":0,
        "total_moto":1,
        "n1":{
            "total":39,
            "light":0,
            "heavy":0,
            "bus":0,
            "moto":0
        },
        "n2":{
            "total":42,
            "light":0,
            "heavy":0,
            "bus":0,
            "moto":0
        },
        "n3":{
            "total":40,
            "light":0,
            "heavy":0,
            "bus":0,
            "moto":0
        },
        "s1":{
            "total":55,
            "light":0,
            "heavy":0,
            "bus":0,
            "moto":0
        },
        "s2":{
            "total":47,
            "light":0,
            "heavy":0,
            "bus":0,
            "moto":0
        },
        "s3":{
            "total":25,
            "light":0,
            "heavy":0,
            "bus":0,
            "moto":0
        }
    }
}